[
  { "term": "real estate agent San Clemente CA", "tier": "primary" },
  { "term": "probate real estate agent Orange County", "tier": "primary" },
  { "term": "selling home during divorce Orange County", "tier": "primary" },
  { "term": "probate real estate California", "tier": "primary" },
  { "term": "estate sale real estate agent San Clemente", "tier": "primary" },
  { "term": "real estate agent Dana Point", "tier": "secondary" },
  { "term": "San Juan Capistrano homes for sale", "tier": "secondary" },
  { "term": "selling inherited property California", "tier": "secondary" },
  { "term": "how long does probate take in California", "tier": "secondary" },
  { "term": "divorce real estate agent Orange County", "tier": "secondary" },
  { "term": "buying a home in San Clemente", "tier": "secondary" },
  { "term": "South Orange County real estate market 2026", "tier": "secondary" },
  { "term": "sell house during probate Orange County", "tier": "secondary" },
  { "term": "court-ordered home sale California", "tier": "secondary" },
  { "term": "coastal Orange County realtor", "tier": "secondary" }
]
